nonebot_plugin_plus_one/__init__.py
nonebot_plugin_plus_one/config.py
nonebot_plugin_plus_one/handler.py
nonebot_plugin_plus_one-0.1.10.dist-info/METADATA
nonebot_plugin_plus_one-0.1.10.dist-info/WHEEL
nonebot_plugin_plus_one-0.1.10.dist-info/RECORD
