Metadata-Version: 2.1
Name: nonebot-plugin-plus-one
Version: 0.1.10
Summary: 全新复读姬，支持文本、图片、表情甚至是转发分享卡片复读，任意群聊触发 +1，姬就 +1。轻巧、专注，不使用任何数据库，不使用任何文件存储
License: MIT
Author: yejue
Author-email: 1145331931@qq.com
Requires-Python: >=3.8,<4.0
Classifier: License :: OSI Approved :: MIT License
Classifier: Programming Language :: Python :: 3
Classifier: Programming Language :: Python :: 3.8
Classifier: Programming Language :: Python :: 3.9
Classifier: Programming Language :: Python :: 3.10
Classifier: Programming Language :: Python :: 3.11
Classifier: Programming Language :: Python :: 3.12
Requires-Dist: nonebot2 (>=2.2,<3.0)
Requires-Dist: nonebot_plugin_session (>=0.3,<0.4)
Project-URL: homepage, https://github.com/yejue/nonebot-plugin-plus-one
Project-URL: repository, https://github.com/yejue/nonebot-plugin-plus-one
